synonym_cli/__init__.py
synonym_cli/__main__.py
synonym_cli/altervista.py
synonym_cli/cli.py
synonym_cli/datamuse.py
synonym_cli/settings.py
synonym_cli/tur.py
synonym_cli-0.3.2.dist-info/METADATA
synonym_cli-0.3.2.dist-info/WHEEL
synonym_cli-0.3.2.dist-info/entry_points.txt
synonym_cli-0.3.2.dist-info/RECORD
