Metadata-Version: 2.4
Name: synonym-cli
Version: 0.3.2
Summary: 🌾Get synonyms and antonyms of words from Thesaurus.com and other sources in your terminal, with rich output.
Project-URL: Homepage, https://github.com/agmmnn/syn
Project-URL: Repository, https://github.com/agmmnn/syn
Project-URL: Changelog, https://github.com/agmmnn/syn/releases
Project-URL: Bug Tracker, https://github.com/agmmnn/syn/issues
Author-email: agmmnn <agmmnn@gmail.com>
Keywords: antonym,cli,synonym,thesaurus
Classifier: Environment :: Console
Classifier: Operating System :: OS Independent
Classifier: Programming Language :: Python :: 3
Classifier: Topic :: Utilities
Requires-Python: >=3.8
Requires-Dist: aiohttp>=3.9.0b0
Requires-Dist: beautifulsoup4>=4.12.2
Requires-Dist: importlib-metadata>=6.8.0
Requires-Dist: requests>=2.31.0
Requires-Dist: rich>=13.6.0
